mov_cli_test/__init__.py
mov_cli_test/scraper.py
mov_cli_test-1.1.7.dist-info/LICENSE
mov_cli_test-1.1.7.dist-info/METADATA
mov_cli_test-1.1.7.dist-info/WHEEL
mov_cli_test-1.1.7.dist-info/top_level.txt
mov_cli_test-1.1.7.dist-info/RECORD
