Metadata-Version: 2.1
Name: mov-cli-test
Version: 1.1.7
Summary: A mov-cli plugin that let's you test mov-cli's capabilities by watching free films and animations in the creative commons.
Author-email: Goldy <goldy@devgoldy.xyz>
License: MIT License
Project-URL: GitHub, https://github.com/THEGOLDENPRO/mov-cli-test
Project-URL: BugTracker, https://github.com/THEGOLDENPRO/mov-cli-test/issues
Keywords: amazing mov-cli plugin
Classifier: Operating System :: Microsoft :: Windows :: Windows 11
Classifier: Operating System :: Microsoft :: Windows :: Windows 10
Classifier: Operating System :: POSIX :: Linux
Classifier: License :: OSI Approved :: MIT License
Classifier: Programming Language :: Python :: 3.8
Classifier: Programming Language :: Python :: 3.9
Classifier: Programming Language :: Python :: 3.10
Classifier: Programming Language :: Python :: 3.11
Requires-Python: >=3.8
License-File: LICENSE
Requires-Dist: pytubefix
Provides-Extra: dev
Requires-Dist: ruff ; extra == 'dev'
Requires-Dist: build ; extra == 'dev'
